<?xml version="1.0" encoding="utf-8"?>
<annotation>
<folder>images</folder>
<filename>0000_84_083.jpg</filename>
<source>
<database>MyDatabase</database>
<annotation>COCO2017</annotation>
<image>flickr</image>
<flickrid>NULL</flickrid>
<annotator>2</annotator>
</source>
<owner>
<flickrid>NULL</flickrid>
<name>Label Studio</name>
</owner>
<size>
<width>1240</width>
<height>1754</height>
<depth>1</depth>
</size>
<segmented>0</segmented>
<object>
<name>chapter</name>
<pose>Unspecified</pose>
<truncated>0</truncated>
<difficult>0</difficult>
<bndbox>
<xmin>133</xmin>
<ymin>392</ymin>
<xmax>1048</xmax>
<ymax>533</ymax>
</bndbox>
</object>
<object>
<name>chapter</name>
<pose>Unspecified</pose>
<truncated>0</truncated>
<difficult>0</difficult>
<bndbox>
<xmin>404</xmin>
<ymin>600</ymin>
<xmax>782</xmax>
<ymax>728</ymax>
</bndbox>
</object>
<object>
<name>content</name>
<pose>Unspecified</pose>
<truncated>0</truncated>
<difficult>0</difficult>
<bndbox>
<xmin>103</xmin>
<ymin>740</ymin>
<xmax>1081</xmax>
<ymax>1575</ymax>
</bndbox>
</object>
<object>
<name>content_pagenumber</name>
<pose>Unspecified</pose>
<truncated>0</truncated>
<difficult>0</difficult>
<bndbox>
<xmin>577</xmin>
<ymin>1616</ymin>
<xmax>614</xmax>
<ymax>1646</ymax>
</bndbox>
</object>
</annotation>
