<?xml version="1.0" encoding="utf-8"?>
<annotation>
<folder>images</folder>
<filename>0000_124_013.jpg</filename>
<source>
<database>MyDatabase</database>
<annotation>COCO2017</annotation>
<image>flickr</image>
<flickrid>NULL</flickrid>
<annotator>2</annotator>
</source>
<owner>
<flickrid>NULL</flickrid>
<name>Label Studio</name>
</owner>
<size>
<width>1240</width>
<height>1754</height>
<depth>1</depth>
</size>
<segmented>0</segmented>
<object>
<name>chapter</name>
<pose>Unspecified</pose>
<truncated>0</truncated>
<difficult>0</difficult>
<bndbox>
<xmin>481</xmin>
<ymin>284</ymin>
<xmax>698</xmax>
<ymax>319</ymax>
</bndbox>
</object>
<object>
<name>TOC_chapter</name>
<pose>Unspecified</pose>
<truncated>0</truncated>
<difficult>0</difficult>
<bndbox>
<xmin>73</xmin>
<ymin>343</ymin>
<xmax>185</xmax>
<ymax>372</ymax>
</bndbox>
</object>
<object>
<name>TOC_chapter</name>
<pose>Unspecified</pose>
<truncated>0</truncated>
<difficult>0</difficult>
<bndbox>
<xmin>90</xmin>
<ymin>379</ymin>
<xmax>1058</xmax>
<ymax>600</ymax>
</bndbox>
</object>
<object>
<name>TOC_pagenumber</name>
<pose>Unspecified</pose>
<truncated>0</truncated>
<difficult>0</difficult>
<bndbox>
<xmin>1086</xmin>
<ymin>377</ymin>
<xmax>1108</xmax>
<ymax>401</ymax>
</bndbox>
</object>
<object>
<name>TOC_pagenumber</name>
<pose>Unspecified</pose>
<truncated>0</truncated>
<difficult>0</difficult>
<bndbox>
<xmin>1086</xmin>
<ymin>346</ymin>
<xmax>1109</xmax>
<ymax>370</ymax>
</bndbox>
</object>
<object>
<name>TOC_chapter</name>
<pose>Unspecified</pose>
<truncated>0</truncated>
<difficult>0</difficult>
<bndbox>
<xmin>85</xmin>
<ymin>605</ymin>
<xmax>1057</xmax>
<ymax>693</ymax>
</bndbox>
</object>
<object>
<name>TOC_pagenumber</name>
<pose>Unspecified</pose>
<truncated>0</truncated>
<difficult>0</difficult>
<bndbox>
<xmin>1074</xmin>
<ymin>600</ymin>
<xmax>1107</xmax>
<ymax>625</ymax>
</bndbox>
</object>
<object>
<name>TOC_chapter</name>
<pose>Unspecified</pose>
<truncated>0</truncated>
<difficult>0</difficult>
<bndbox>
<xmin>83</xmin>
<ymin>701</ymin>
<xmax>1052</xmax>
<ymax>858</ymax>
</bndbox>
</object>
<object>
<name>TOC_pagenumber</name>
<pose>Unspecified</pose>
<truncated>0</truncated>
<difficult>0</difficult>
<bndbox>
<xmin>1077</xmin>
<ymin>700</ymin>
<xmax>1107</xmax>
<ymax>722</ymax>
</bndbox>
</object>
<object>
<name>TOC_chapter</name>
<pose>Unspecified</pose>
<truncated>0</truncated>
<difficult>0</difficult>
<bndbox>
<xmin>85</xmin>
<ymin>863</ymin>
<xmax>1054</xmax>
<ymax>1153</ymax>
</bndbox>
</object>
<object>
<name>TOC_pagenumber</name>
<pose>Unspecified</pose>
<truncated>0</truncated>
<difficult>0</difficult>
<bndbox>
<xmin>1075</xmin>
<ymin>860</ymin>
<xmax>1109</xmax>
<ymax>886</ymax>
</bndbox>
</object>
<object>
<name>TOC_chapter</name>
<pose>Unspecified</pose>
<truncated>0</truncated>
<difficult>0</difficult>
<bndbox>
<xmin>86</xmin>
<ymin>1156</ymin>
<xmax>1054</xmax>
<ymax>1310</ymax>
</bndbox>
</object>
<object>
<name>TOC_pagenumber</name>
<pose>Unspecified</pose>
<truncated>0</truncated>
<difficult>0</difficult>
<bndbox>
<xmin>1065</xmin>
<ymin>1153</ymin>
<xmax>1109</xmax>
<ymax>1177</ymax>
</bndbox>
</object>
<object>
<name>TOC_chapter</name>
<pose>Unspecified</pose>
<truncated>0</truncated>
<difficult>0</difficult>
<bndbox>
<xmin>87</xmin>
<ymin>1314</ymin>
<xmax>1054</xmax>
<ymax>1469</ymax>
</bndbox>
</object>
<object>
<name>TOC_pagenumber</name>
<pose>Unspecified</pose>
<truncated>0</truncated>
<difficult>0</difficult>
<bndbox>
<xmin>1065</xmin>
<ymin>1314</ymin>
<xmax>1107</xmax>
<ymax>1339</ymax>
</bndbox>
</object>
<object>
<name>TOC_chapter</name>
<pose>Unspecified</pose>
<truncated>0</truncated>
<difficult>0</difficult>
<bndbox>
<xmin>87</xmin>
<ymin>1476</ymin>
<xmax>1052</xmax>
<ymax>1637</ymax>
</bndbox>
</object>
<object>
<name>TOC_pagenumber</name>
<pose>Unspecified</pose>
<truncated>0</truncated>
<difficult>0</difficult>
<bndbox>
<xmin>1062</xmin>
<ymin>1475</ymin>
<xmax>1107</xmax>
<ymax>1497</ymax>
</bndbox>
</object>
<object>
<name>content_pagenumber</name>
<pose>Unspecified</pose>
<truncated>0</truncated>
<difficult>0</difficult>
<bndbox>
<xmin>577</xmin>
<ymin>1638</ymin>
<xmax>603</xmax>
<ymax>1665</ymax>
</bndbox>
</object>
</annotation>
