<?xml version="1.0" encoding="utf-8"?>
<annotation>
<folder>images</folder>
<filename>0000_133_013.jpg</filename>
<source>
<database>MyDatabase</database>
<annotation>COCO2017</annotation>
<image>flickr</image>
<flickrid>NULL</flickrid>
<annotator>1</annotator>
</source>
<owner>
<flickrid>NULL</flickrid>
<name>Label Studio</name>
</owner>
<size>
<width>1240</width>
<height>1754</height>
<depth>1</depth>
</size>
<segmented>0</segmented>
<object>
<name>content_pagenumber</name>
<pose>Unspecified</pose>
<truncated>0</truncated>
<difficult>0</difficult>
<bndbox>
<xmin>1073</xmin>
<ymin>1667</ymin>
<xmax>1100</xmax>
<ymax>1704</ymax>
</bndbox>
</object>
<object>
<name>chapter</name>
<pose>Unspecified</pose>
<truncated>0</truncated>
<difficult>0</difficult>
<bndbox>
<xmin>67</xmin>
<ymin>108</ymin>
<xmax>304</xmax>
<ymax>148</ymax>
</bndbox>
</object>
<object>
<name>chapter</name>
<pose>Unspecified</pose>
<truncated>0</truncated>
<difficult>0</difficult>
<bndbox>
<xmin>77</xmin>
<ymin>463</ymin>
<xmax>419</xmax>
<ymax>496</ymax>
</bndbox>
</object>
<object>
<name>chapter</name>
<pose>Unspecified</pose>
<truncated>0</truncated>
<difficult>0</difficult>
<bndbox>
<xmin>74</xmin>
<ymin>719</ymin>
<xmax>638</xmax>
<ymax>765</ymax>
</bndbox>
</object>
<object>
<name>chapter</name>
<pose>Unspecified</pose>
<truncated>0</truncated>
<difficult>0</difficult>
<bndbox>
<xmin>77</xmin>
<ymin>1071</ymin>
<xmax>835</xmax>
<ymax>1117</ymax>
</bndbox>
</object>
<object>
<name>content</name>
<pose>Unspecified</pose>
<truncated>0</truncated>
<difficult>0</difficult>
<bndbox>
<xmin>70</xmin>
<ymin>166</ymin>
<xmax>1094</xmax>
<ymax>416</ymax>
</bndbox>
</object>
<object>
<name>content</name>
<pose>Unspecified</pose>
<truncated>0</truncated>
<difficult>0</difficult>
<bndbox>
<xmin>74</xmin>
<ymin>518</ymin>
<xmax>1098</xmax>
<ymax>675</ymax>
</bndbox>
</object>
<object>
<name>content</name>
<pose>Unspecified</pose>
<truncated>0</truncated>
<difficult>0</difficult>
<bndbox>
<xmin>74</xmin>
<ymin>778</ymin>
<xmax>1101</xmax>
<ymax>1034</ymax>
</bndbox>
</object>
<object>
<name>content</name>
<pose>Unspecified</pose>
<truncated>0</truncated>
<difficult>0</difficult>
<bndbox>
<xmin>77</xmin>
<ymin>1136</ymin>
<xmax>1101</xmax>
<ymax>1435</ymax>
</bndbox>
</object>
</annotation>
